{
    "AA120": "311",
    "AA125": "318",
    "AAInitial": "59",
    "AAKai": "0",
    "AAKai120": "0",
    "AAKai125": "0",
    "AAMax": "285",
    "ASW120": "0",
    "ASW125": "0",
    "ASWInitial": "0",
    "ASWKai": "0",
    "ASWKai120": "0",
    "ASWKai125": "0",
    "ASWMax": "0",
    "Acc120": "90",
    "Acc125": "92",
    "AccInitial": "31",
    "AccKai": "0",
    "AccKai120": "0",
    "AccKai125": "0",
    "AccMax": "80",
    "Air120": "394",
    "Air125": "399",
    "AirInitial": "75",
    "AirKai": "0",
    "AirKai120": "0",
    "AirKai125": "0",
    "AirMax": "374",
    "Ammo": "0",
    "Armor": "Medium",
    "Artist": "Alisa",
    "ArtistLink": "[https://weibo.com/u/6056658230 \u599e\u599e\u540c\u5b66\u63d0\u4e0d\u8d77\u52b2]",
    "ArtistPixiv": "[https://www.pixiv.net/member.php?id=1966676 \u9ed2\u306e\u685c]",
    "ArtistTwitter": "[https://twitter.com/16119831274 Alisa]",
    "CNName": "\u5c0f\u51f0",
    "Class": "Akagi",
    "ConstructTime": "04:35:00",
    "ConsumptionInitial": "4",
    "ConsumptionMax": "12",
    "Eq1BaseMax": "3",
    "Eq1EffInit": "110%",
    "Eq1EffInitMax": "125%",
    "Eq1Type": "Fighter",
    "Eq2BaseMax": "2",
    "Eq2EffInit": "100%",
    "Eq2EffInitMax": "115%",
    "Eq2Type": "Dive Bomber",
    "Eq3BaseMax": "3",
    "Eq3EffInit": "110%",
    "Eq3EffInitMax": "125%",
    "Eq3Type": "Torpedo Bomber",
    "Evade120": "54",
    "Evade125": "56",
    "EvadeInitial": "13",
    "EvadeKai": "0",
    "EvadeKai120": "0",
    "EvadeKai125": "0",
    "EvadeMax": "47",
    "Fire120": "0",
    "Fire125": "0",
    "FireInitial": "0",
    "FireKai": "0",
    "FireKai120": "0",
    "FireKai125": "0",
    "FireMax": "0",
    "Health120": "6250",
    "Health125": "6395",
    "HealthInitial": "1077",
    "HealthKai": "0",
    "HealthKai120": "0",
    "HealthKai125": "0",
    "HealthMax": "5673",
    "JPName": "\u5c0f\u8d64\u57ce",
    "KRName": "\uaf2c\ub9c8 \uc544\uce74\uae30",
    "Luck": "42",
    "Name": "Akagi-chan",
    "Nationality": "Sakura Empire",
    "Oxygen": "0",
    "Rarity": "Elite",
    "Reload120": "125",
    "Reload125": "126",
    "ReloadInitial": "46",
    "ReloadKai": "0",
    "ReloadKai120": "0",
    "ReloadKai125": "0",
    "ReloadMax": "118",
    "ShipGroup": "Child",
    "ShipID": "384",
    "Speed": "31",
    "SpeedKai": "0",
    "Torp120": "0",
    "Torp125": "0",
    "TorpInitial": "0",
    "TorpKai": "0",
    "TorpKai120": "0",
    "TorpKai125": "0",
    "TorpMax": "0",
    "Type": "Aircraft Carrier",
    "VA": "[[:wikipedia:Mai_Nakahara|Mai Nakahara]]"
}