{
    "AA120": "0",
    "AA125": "0",
    "AAInitial": "0",
    "AAKai": "0",
    "AAKai120": "0",
    "AAKai125": "0",
    "AAMax": "0",
    "ASW120": "0",
    "ASW125": "0",
    "ASWInitial": "0",
    "ASWKai": "0",
    "ASWKai120": "0",
    "ASWKai125": "0",
    "ASWMax": "0",
    "Acc120": "166",
    "Acc125": "171",
    "AccInitial": "57",
    "AccKai": "0",
    "AccKai120": "0",
    "AccKai125": "0",
    "AccMax": "148",
    "Air120": "0",
    "Air125": "0",
    "AirInitial": "0",
    "AirKai": "0",
    "AirKai120": "0",
    "AirKai125": "0",
    "AirMax": "0",
    "Ammo": "2",
    "Armor": "Light",
    "Artist": "\u68a6\u54b2\u67ab",
    "ArtistLink": "[http://weibo.com/u/3558369570 \u68a6\u54b2\u67ab]",
    "ArtistPixiv": "[https://www.pixiv.net/member.php?id=1023957 \u304b\u3048\u3067]",
    "ArtistTwitter": "[https://twitter.com/yumesaki_kaede/ \u304b\u3048\u3067]",
    "CNName": "U-557",
    "Class": "Type VIIC",
    "ConstructTime": "00:13:00",
    "ConsumptionInitial": "2",
    "ConsumptionMax": "6",
    "Eq1BaseMax": "2",
    "Eq1EffInit": "110%",
    "Eq1EffInitMax": "125%",
    "Eq1Type": "Submarine Torpedoes",
    "Eq2BaseMax": "2",
    "Eq2EffInit": "105%",
    "Eq2EffInitMax": "120%",
    "Eq2Type": "Submarine Torpedoes",
    "Eq3BaseMax": "1",
    "Eq3EffInit": "85%",
    "Eq3EffInitMax": "85%",
    "Eq3Type": "DD Guns",
    "Evade120": "37",
    "Evade125": "38",
    "EvadeInitial": "7",
    "EvadeKai": "0",
    "EvadeKai120": "0",
    "EvadeKai125": "0",
    "EvadeMax": "32",
    "Fire120": "44",
    "Fire125": "44",
    "FireInitial": "8",
    "FireKai": "0",
    "FireKai120": "0",
    "FireKai125": "0",
    "FireMax": "41",
    "Health120": "1261",
    "Health125": "1292",
    "HealthInitial": "203",
    "HealthKai": "0",
    "HealthKai120": "0",
    "HealthKai125": "0",
    "HealthMax": "1139",
    "JPName": "U-557",
    "Luck": "18",
    "Name": "U-557",
    "Nationality": "Iron Blood",
    "Oxygen": "188",
    "Rarity": "Elite",
    "Reload120": "84",
    "Reload125": "85",
    "ReloadInitial": "31",
    "ReloadKai": "0",
    "ReloadKai120": "0",
    "ReloadKai125": "0",
    "ReloadMax": "79",
    "ShipGroup": "Standard",
    "ShipID": "344",
    "Speed": "14",
    "SpeedKai": "0",
    "StatBonus120": "1",
    "StatBonus120Type": "Torpedo",
    "StatBonusCollect": "2",
    "StatBonusCollectType": "Evasion",
    "TechPoint120": "12",
    "TechPointCollect": "8",
    "TechPointMLB": "16",
    "Torp120": "499",
    "Torp125": "505",
    "TorpInitial": "96",
    "TorpKai": "0",
    "TorpKai120": "0",
    "TorpKai125": "0",
    "TorpMax": "474",
    "Type": "Submarine",
    "VA": "[[:wikipedia:Azumi_Asakura|Azumi Asakura]]"
}
